{
 "custom_fields": [
  {
   "_assign": null,
   "_comments": null,
   "_liked_by": null,
   "_user_tags": null,
   "allow_in_quick_entry": 0,
   "allow_on_submit": 0,
   "bold": 0,
   "collapsible": 0,
   "collapsible_depends_on": null,
   "columns": 0,
   "creation": "2022-05-25 16:54:38.834201",
   "default": null,
   "depends_on": null,
   "description": null,
   "docstatus": 0,
   "dt": "Sales Invoice",
   "fetch_from": "company.tax_id",
   "fetch_if_empty": 0,
   "fieldname": "company_trn",
   "fieldtype": "Read Only",
   "hidden": 0,
   "hide_border": 0,
   "hide_days": 0,
   "hide_seconds": 0,
   "idx": 57,
   "ignore_user_permissions": 0,
   "ignore_xss_filter": 0,
   "in_global_search": 0,
   "in_list_view": 0,
   "in_preview": 0,
   "in_standard_filter": 0,
   "insert_after": "company_address",
   "label": "Company TRN",
   "length": 0,
   "mandatory_depends_on": null,
   "modified": "2022-05-29 15:12:56.907539",
   "modified_by": "Administrator",
   "name": "Sales Invoice-company_trn",
   "no_copy": 0,
   "non_negative": 0,
   "options": null,
   "owner": "Administrator",
   "parent": null,
   "parentfield": null,
   "parenttype": null,
   "permlevel": 0,
   "precision": "",
   "print_hide": 1,
   "print_hide_if_no_value": 0,
   "print_width": null,
   "read_only": 0,
   "read_only_depends_on": null,
   "report_hide": 0,
   "reqd": 0,
   "search_index": 0,
   "translatable": 1,
   "unique": 0,
   "width": null
  },
  {
   "_assign": null,
   "_comments": null,
   "_liked_by": null,
   "_user_tags": null,
   "allow_in_quick_entry": 0,
   "allow_on_submit": 0,
   "bold": 0,
   "collapsible": 0,
   "collapsible_depends_on": null,
   "columns": 0,
   "creation": "2022-05-25 16:54:38.882923",
   "default": null,
   "depends_on": null,
   "description": null,
   "docstatus": 0,
   "dt": "Sales Invoice",
   "fetch_from": "customer.customer_name_in_arabic",
   "fetch_if_empty": 0,
   "fieldname": "customer_name_in_arabic",
   "fieldtype": "Read Only",
   "hidden": 0,
   "hide_border": 0,
   "hide_days": 0,
   "hide_seconds": 0,
   "idx": 6,
   "ignore_user_permissions": 0,
   "ignore_xss_filter": 0,
   "in_global_search": 0,
   "in_list_view": 0,
   "in_preview": 0,
   "in_standard_filter": 0,
   "insert_after": "customer_name",
   "label": "Customer Name in Arabic",
   "length": 0,
   "mandatory_depends_on": null,
   "modified": "2022-05-29 15:12:57.088314",
   "modified_by": "Administrator",
   "name": "Sales Invoice-customer_name_in_arabic",
   "no_copy": 0,
   "non_negative": 0,
   "options": null,
   "owner": "Administrator",
   "parent": null,
   "parentfield": null,
   "parenttype": null,
   "permlevel": 0,
   "precision": "",
   "print_hide": 1,
   "print_hide_if_no_value": 0,
   "print_width": null,
   "read_only": 0,
   "read_only_depends_on": null,
   "report_hide": 0,
   "reqd": 0,
   "search_index": 0,
   "translatable": 1,
   "unique": 0,
   "width": null
  },
  {
   "_assign": null,
   "_comments": null,
   "_liked_by": null,
   "_user_tags": null,
   "allow_in_quick_entry": 0,
   "allow_on_submit": 0,
   "bold": 0,
   "collapsible": 0,
   "collapsible_depends_on": null,
   "columns": 0,
   "creation": "2022-05-25 16:54:38.933626",
   "default": null,
   "depends_on": null,
   "description": null,
   "docstatus": 0,
   "dt": "Sales Invoice",
   "fetch_from": "company_address.emirate",
   "fetch_if_empty": 0,
   "fieldname": "vat_emirate",
   "fieldtype": "Select",
   "hidden": 0,
   "hide_border": 0,
   "hide_days": 0,
   "hide_seconds": 0,
   "idx": 171,
   "ignore_user_permissions": 0,
   "ignore_xss_filter": 0,
   "in_global_search": 0,
   "in_list_view": 0,
   "in_preview": 0,
   "in_standard_filter": 0,
   "insert_after": "permit_no",
   "label": "VAT Emirate",
   "length": 0,
   "mandatory_depends_on": null,
   "modified": "2022-05-29 15:12:57.265951",
   "modified_by": "Administrator",
   "name": "Sales Invoice-vat_emirate",
   "no_copy": 0,
   "non_negative": 0,
   "options": "\nAbu Dhabi\nAjman\nDubai\nFujairah\nRas Al Khaimah\nSharjah\nUmm Al Quwain",
   "owner": "Administrator",
   "parent": null,
   "parentfield": null,
   "parenttype": null,
   "permlevel": 0,
   "precision": "",
   "print_hide": 0,
   "print_hide_if_no_value": 0,
   "print_width": null,
   "read_only": 0,
   "read_only_depends_on": null,
   "report_hide": 0,
   "reqd": 0,
   "search_index": 0,
   "translatable": 1,
   "unique": 0,
   "width": null
  },
  {
   "_assign": null,
   "_comments": null,
   "_liked_by": null,
   "_user_tags": null,
   "allow_in_quick_entry": 0,
   "allow_on_submit": 0,
   "bold": 0,
   "collapsible": 0,
   "collapsible_depends_on": null,
   "columns": 0,
   "creation": "2022-05-25 16:54:38.984500",
   "default": "0",
   "depends_on": null,
   "description": null,
   "docstatus": 0,
   "dt": "Sales Invoice",
   "fetch_from": null,
   "fetch_if_empty": 0,
   "fieldname": "tourist_tax_return",
   "fieldtype": "Currency",
   "hidden": 0,
   "hide_border": 0,
   "hide_days": 0,
   "hide_seconds": 0,
   "idx": 211,
   "ignore_user_permissions": 0,
   "ignore_xss_filter": 0,
   "in_global_search": 0,
   "in_list_view": 0,
   "in_preview": 0,
   "in_standard_filter": 0,
   "insert_after": "against_income_account",
   "label": "Tax Refund provided to Tourists (AED)",
   "length": 0,
   "mandatory_depends_on": null,
   "modified": "2022-05-29 15:12:57.437171",
   "modified_by": "Administrator",
   "name": "Sales Invoice-tourist_tax_return",
   "no_copy": 0,
   "non_negative": 0,
   "options": null,
   "owner": "Administrator",
   "parent": null,
   "parentfield": null,
   "parenttype": null,
   "permlevel": 0,
   "precision": "",
   "print_hide": 1,
   "print_hide_if_no_value": 0,
   "print_width": null,
   "read_only": 0,
   "read_only_depends_on": null,
   "report_hide": 0,
   "reqd": 0,
   "search_index": 0,
   "translatable": 1,
   "unique": 0,
   "width": null
  },
  {
   "_assign": null,
   "_comments": null,
   "_liked_by": null,
   "_user_tags": null,
   "allow_in_quick_entry": 0,
   "allow_on_submit": 0,
   "bold": 0,
   "collapsible": 1,
   "collapsible_depends_on": null,
   "columns": 0,
   "creation": "2022-05-25 16:54:39.034426",
   "default": null,
   "depends_on": null,
   "description": null,
   "docstatus": 0,
   "dt": "Sales Invoice",
   "fetch_from": null,
   "fetch_if_empty": 0,
   "fieldname": "vat_section",
   "fieldtype": "Section Break",
   "hidden": 0,
   "hide_border": 0,
   "hide_days": 0,
   "hide_seconds": 0,
   "idx": 169,
   "ignore_user_permissions": 0,
   "ignore_xss_filter": 0,
   "in_global_search": 0,
   "in_list_view": 0,
   "in_preview": 0,
   "in_standard_filter": 0,
   "insert_after": "print_without_amount",
   "label": "VAT Details",
   "length": 0,
   "mandatory_depends_on": null,
   "modified": "2022-05-29 15:12:57.599460",
   "modified_by": "Administrator",
   "name": "Sales Invoice-vat_section",
   "no_copy": 0,
   "non_negative": 0,
   "options": null,
   "owner": "Administrator",
   "parent": null,
   "parentfield": null,
   "parenttype": null,
   "permlevel": 0,
   "precision": "",
   "print_hide": 1,
   "print_hide_if_no_value": 0,
   "print_width": null,
   "read_only": 0,
   "read_only_depends_on": null,
   "report_hide": 0,
   "reqd": 0,
   "search_index": 0,
   "translatable": 1,
   "unique": 0,
   "width": null
  },
  {
   "_assign": null,
   "_comments": null,
   "_liked_by": null,
   "_user_tags": null,
   "allow_in_quick_entry": 0,
   "allow_on_submit": 0,
   "bold": 0,
   "collapsible": 0,
   "collapsible_depends_on": null,
   "columns": 0,
   "creation": "2022-05-25 16:54:39.085119",
   "default": null,
   "depends_on": null,
   "description": null,
   "docstatus": 0,
   "dt": "Sales Invoice",
   "fetch_from": null,
   "fetch_if_empty": 0,
   "fieldname": "permit_no",
   "fieldtype": "Data",
   "hidden": 0,
   "hide_border": 0,
   "hide_days": 0,
   "hide_seconds": 0,
   "idx": 170,
   "ignore_user_permissions": 0,
   "ignore_xss_filter": 0,
   "in_global_search": 0,
   "in_list_view": 0,
   "in_preview": 0,
   "in_standard_filter": 0,
   "insert_after": "vat_section",
   "label": "Permit Number",
   "length": 0,
   "mandatory_depends_on": null,
   "modified": "2022-05-29 15:12:57.738062",
   "modified_by": "Administrator",
   "name": "Sales Invoice-permit_no",
   "no_copy": 0,
   "non_negative": 0,
   "options": null,
   "owner": "Administrator",
   "parent": null,
   "parentfield": null,
   "parenttype": null,
   "permlevel": 0,
   "precision": "",
   "print_hide": 1,
   "print_hide_if_no_value": 0,
   "print_width": null,
   "read_only": 0,
   "read_only_depends_on": null,
   "report_hide": 0,
   "reqd": 0,
   "search_index": 0,
   "translatable": 1,
   "unique": 0,
   "width": null
  },
  {
   "_assign": null,
   "_comments": null,
   "_liked_by": null,
   "_user_tags": null,
   "allow_in_quick_entry": 0,
   "allow_on_submit": 0,
   "bold": 0,
   "collapsible": 0,
   "collapsible_depends_on": null,
   "columns": 0,
   "creation": "2022-05-29 15:21:14.427930",
   "default": null,
   "depends_on": null,
   "description": null,
   "docstatus": 0,
   "dt": "Sales Invoice",
   "fetch_from": null,
   "fetch_if_empty": 0,
   "fieldname": "marketing_expenses_dimension",
   "fieldtype": "Link",
   "hidden": 0,
   "hide_border": 0,
   "hide_days": 0,
   "hide_seconds": 0,
   "idx": 36,
   "ignore_user_permissions": 0,
   "ignore_xss_filter": 0,
   "in_global_search": 0,
   "in_list_view": 0,
   "in_preview": 0,
   "in_standard_filter": 0,
   "insert_after": "project_expenses_dimension",
   "label": "Marketing Expenses Dimension",
   "length": 0,
   "mandatory_depends_on": null,
   "modified": "2022-05-29 15:21:14.427930",
   "modified_by": "Administrator",
   "name": "Sales Invoice-marketing_expenses_dimension",
   "no_copy": 0,
   "non_negative": 0,
   "options": "Marketing Expenses Dimension",
   "owner": "Administrator",
   "parent": null,
   "parentfield": null,
   "parenttype": null,
   "permlevel": 0,
   "precision": "",
   "print_hide": 0,
   "print_hide_if_no_value": 0,
   "print_width": null,
   "read_only": 0,
   "read_only_depends_on": null,
   "report_hide": 0,
   "reqd": 0,
   "search_index": 0,
   "translatable": 1,
   "unique": 0,
   "width": null
  },
  {
   "_assign": null,
   "_comments": null,
   "_liked_by": null,
   "_user_tags": null,
   "allow_in_quick_entry": 0,
   "allow_on_submit": 0,
   "bold": 0,
   "collapsible": 0,
   "collapsible_depends_on": null,
   "columns": 0,
   "creation": "2022-05-29 15:25:04.659881",
   "default": null,
   "depends_on": null,
   "description": null,
   "docstatus": 0,
   "dt": "Sales Invoice",
   "fetch_from": null,
   "fetch_if_empty": 0,
   "fieldname": "visa_expenses_dimension",
   "fieldtype": "Link",
   "hidden": 0,
   "hide_border": 0,
   "hide_days": 0,
   "hide_seconds": 0,
   "idx": 24,
   "ignore_user_permissions": 0,
   "ignore_xss_filter": 0,
   "in_global_search": 0,
   "in_list_view": 0,
   "in_preview": 0,
   "in_standard_filter": 0,
   "insert_after": "accounting_dimensions_section",
   "label": "Visa Expenses Dimension",
   "length": 0,
   "mandatory_depends_on": null,
   "modified": "2022-05-29 15:25:04.659881",
   "modified_by": "Administrator",
   "name": "Sales Invoice-visa_expenses_dimension",
   "no_copy": 0,
   "non_negative": 0,
   "options": "Visa Expenses Dimension",
   "owner": "Administrator",
   "parent": null,
   "parentfield": null,
   "parenttype": null,
   "permlevel": 0,
   "precision": "",
   "print_hide": 0,
   "print_hide_if_no_value": 0,
   "print_width": null,
   "read_only": 0,
   "read_only_depends_on": null,
   "report_hide": 0,
   "reqd": 0,
   "search_index": 0,
   "translatable": 1,
   "unique": 0,
   "width": null
  },
  {
   "_assign": null,
   "_comments": null,
   "_liked_by": null,
   "_user_tags": null,
   "allow_in_quick_entry": 0,
   "allow_on_submit": 0,
   "bold": 0,
   "collapsible": 0,
   "collapsible_depends_on": null,
   "columns": 0,
   "creation": "2022-05-29 15:26:38.172715",
   "default": null,
   "depends_on": null,
   "description": null,
   "docstatus": 0,
   "dt": "Sales Invoice",
   "fetch_from": null,
   "fetch_if_empty": 0,
   "fieldname": "project_expenses_dimension",
   "fieldtype": "Link",
   "hidden": 0,
   "hide_border": 0,
   "hide_days": 0,
   "hide_seconds": 0,
   "idx": 35,
   "ignore_user_permissions": 0,
   "ignore_xss_filter": 0,
   "in_global_search": 0,
   "in_list_view": 0,
   "in_preview": 0,
   "in_standard_filter": 0,
   "insert_after": "related_party_dimension",
   "label": "Project Expenses Dimension",
   "length": 0,
   "mandatory_depends_on": null,
   "modified": "2022-05-29 15:26:38.172715",
   "modified_by": "Administrator",
   "name": "Sales Invoice-project_expenses_dimension",
   "no_copy": 0,
   "non_negative": 0,
   "options": "Project Expenses Dimension",
   "owner": "Administrator",
   "parent": null,
   "parentfield": null,
   "parenttype": null,
   "permlevel": 0,
   "precision": "",
   "print_hide": 0,
   "print_hide_if_no_value": 0,
   "print_width": null,
   "read_only": 0,
   "read_only_depends_on": null,
   "report_hide": 0,
   "reqd": 0,
   "search_index": 0,
   "translatable": 1,
   "unique": 0,
   "width": null
  },
  {
   "_assign": null,
   "_comments": null,
   "_liked_by": null,
   "_user_tags": null,
   "allow_in_quick_entry": 0,
   "allow_on_submit": 0,
   "bold": 0,
   "collapsible": 0,
   "collapsible_depends_on": null,
   "columns": 0,
   "creation": "2022-05-29 15:27:44.276772",
   "default": null,
   "depends_on": null,
   "description": null,
   "docstatus": 0,
   "dt": "Sales Invoice",
   "fetch_from": null,
   "fetch_if_empty": 0,
   "fieldname": "motor_vehicle_expenses_dimension",
   "fieldtype": "Link",
   "hidden": 0,
   "hide_border": 0,
   "hide_days": 0,
   "hide_seconds": 0,
   "idx": 27,
   "ignore_user_permissions": 0,
   "ignore_xss_filter": 0,
   "in_global_search": 0,
   "in_list_view": 0,
   "in_preview": 0,
   "in_standard_filter": 0,
   "insert_after": "other_assets_dimension",
   "label": "Motor Vehicle Expenses Dimension",
   "length": 0,
   "mandatory_depends_on": null,
   "modified": "2022-05-29 15:27:44.276772",
   "modified_by": "Administrator",
   "name": "Sales Invoice-motor_vehicle_expenses_dimension",
   "no_copy": 0,
   "non_negative": 0,
   "options": "Motor Vehicle Expenses Dimension",
   "owner": "Administrator",
   "parent": null,
   "parentfield": null,
   "parenttype": null,
   "permlevel": 0,
   "precision": "",
   "print_hide": 0,
   "print_hide_if_no_value": 0,
   "print_width": null,
   "read_only": 0,
   "read_only_depends_on": null,
   "report_hide": 0,
   "reqd": 0,
   "search_index": 0,
   "translatable": 1,
   "unique": 0,
   "width": null
  },
  {
   "_assign": null,
   "_comments": null,
   "_liked_by": null,
   "_user_tags": null,
   "allow_in_quick_entry": 0,
   "allow_on_submit": 0,
   "bold": 0,
   "collapsible": 0,
   "collapsible_depends_on": null,
   "columns": 0,
   "creation": "2022-05-29 15:29:32.229514",
   "default": null,
   "depends_on": null,
   "description": null,
   "docstatus": 0,
   "dt": "Sales Invoice",
   "fetch_from": null,
   "fetch_if_empty": 0,
   "fieldname": "direct_expenses_dimension",
   "fieldtype": "Link",
   "hidden": 0,
   "hide_border": 0,
   "hide_days": 0,
   "hide_seconds": 0,
   "idx": 37,
   "ignore_user_permissions": 0,
   "ignore_xss_filter": 0,
   "in_global_search": 0,
   "in_list_view": 0,
   "in_preview": 0,
   "in_standard_filter": 0,
   "insert_after": "marketing_expenses_dimension",
   "label": "Direct Expenses Dimension",
   "length": 0,
   "mandatory_depends_on": null,
   "modified": "2022-05-29 15:29:32.229514",
   "modified_by": "Administrator",
   "name": "Sales Invoice-direct_expenses_dimension",
   "no_copy": 0,
   "non_negative": 0,
   "options": "Direct Expenses Dimension",
   "owner": "Administrator",
   "parent": null,
   "parentfield": null,
   "parenttype": null,
   "permlevel": 0,
   "precision": "",
   "print_hide": 0,
   "print_hide_if_no_value": 0,
   "print_width": null,
   "read_only": 0,
   "read_only_depends_on": null,
   "report_hide": 0,
   "reqd": 0,
   "search_index": 0,
   "translatable": 1,
   "unique": 0,
   "width": null
  },
  {
   "_assign": null,
   "_comments": null,
   "_liked_by": null,
   "_user_tags": null,
   "allow_in_quick_entry": 0,
   "allow_on_submit": 0,
   "bold": 0,
   "collapsible": 0,
   "collapsible_depends_on": null,
   "columns": 0,
   "creation": "2022-05-29 15:30:25.892933",
   "default": null,
   "depends_on": null,
   "description": null,
   "docstatus": 0,
   "dt": "Sales Invoice",
   "fetch_from": null,
   "fetch_if_empty": 0,
   "fieldname": "vehicle_loan_dimension",
   "fieldtype": "Link",
   "hidden": 0,
   "hide_border": 0,
   "hide_days": 0,
   "hide_seconds": 0,
   "idx": 25,
   "ignore_user_permissions": 0,
   "ignore_xss_filter": 0,
   "in_global_search": 0,
   "in_list_view": 0,
   "in_preview": 0,
   "in_standard_filter": 0,
   "insert_after": "visa_expenses_dimension",
   "label": "Vehicle Loan Dimension",
   "length": 0,
   "mandatory_depends_on": null,
   "modified": "2022-05-29 15:30:25.892933",
   "modified_by": "Administrator",
   "name": "Sales Invoice-vehicle_loan_dimension",
   "no_copy": 0,
   "non_negative": 0,
   "options": "Vehicle Loan Dimension",
   "owner": "Administrator",
   "parent": null,
   "parentfield": null,
   "parenttype": null,
   "permlevel": 0,
   "precision": "",
   "print_hide": 0,
   "print_hide_if_no_value": 0,
   "print_width": null,
   "read_only": 0,
   "read_only_depends_on": null,
   "report_hide": 0,
   "reqd": 0,
   "search_index": 0,
   "translatable": 1,
   "unique": 0,
   "width": null
  },
  {
   "_assign": null,
   "_comments": null,
   "_liked_by": null,
   "_user_tags": null,
   "allow_in_quick_entry": 0,
   "allow_on_submit": 0,
   "bold": 0,
   "collapsible": 0,
   "collapsible_depends_on": null,
   "columns": 0,
   "creation": "2022-05-29 15:31:37.947048",
   "default": null,
   "depends_on": null,
   "description": null,
   "docstatus": 0,
   "dt": "Sales Invoice",
   "fetch_from": null,
   "fetch_if_empty": 0,
   "fieldname": "accrued_expenses_dimension",
   "fieldtype": "Link",
   "hidden": 0,
   "hide_border": 0,
   "hide_days": 0,
   "hide_seconds": 0,
   "idx": 39,
   "ignore_user_permissions": 0,
   "ignore_xss_filter": 0,
   "in_global_search": 0,
   "in_list_view": 0,
   "in_preview": 0,
   "in_standard_filter": 0,
   "insert_after": "deposit_assets_dimension",
   "label": "Accrued Expenses Dimension",
   "length": 0,
   "mandatory_depends_on": null,
   "modified": "2022-05-29 15:31:37.947048",
   "modified_by": "Administrator",
   "name": "Sales Invoice-accrued_expenses_dimension",
   "no_copy": 0,
   "non_negative": 0,
   "options": "Accrued Expenses Dimension",
   "owner": "Administrator",
   "parent": null,
   "parentfield": null,
   "parenttype": null,
   "permlevel": 0,
   "precision": "",
   "print_hide": 0,
   "print_hide_if_no_value": 0,
   "print_width": null,
   "read_only": 0,
   "read_only_depends_on": null,
   "report_hide": 0,
   "reqd": 0,
   "search_index": 0,
   "translatable": 1,
   "unique": 0,
   "width": null
  },
  {
   "_assign": null,
   "_comments": null,
   "_liked_by": null,
   "_user_tags": null,
   "allow_in_quick_entry": 0,
   "allow_on_submit": 0,
   "bold": 0,
   "collapsible": 0,
   "collapsible_depends_on": null,
   "columns": 0,
   "creation": "2022-05-29 15:32:34.956865",
   "default": null,
   "depends_on": null,
   "description": null,
   "docstatus": 0,
   "dt": "Sales Invoice",
   "fetch_from": null,
   "fetch_if_empty": 0,
   "fieldname": "capital_account_dimension",
   "fieldtype": "Link",
   "hidden": 0,
   "hide_border": 0,
   "hide_days": 0,
   "hide_seconds": 0,
   "idx": 30,
   "ignore_user_permissions": 0,
   "ignore_xss_filter": 0,
   "in_global_search": 0,
   "in_list_view": 0,
   "in_preview": 0,
   "in_standard_filter": 0,
   "insert_after": "cash_dimension",
   "label": "Capital Account Dimension",
   "length": 0,
   "mandatory_depends_on": null,
   "modified": "2022-05-29 15:32:34.956865",
   "modified_by": "Administrator",
   "name": "Sales Invoice-capital_account_dimension",
   "no_copy": 0,
   "non_negative": 0,
   "options": "Capital Account Dimension",
   "owner": "Administrator",
   "parent": null,
   "parentfield": null,
   "parenttype": null,
   "permlevel": 0,
   "precision": "",
   "print_hide": 0,
   "print_hide_if_no_value": 0,
   "print_width": null,
   "read_only": 0,
   "read_only_depends_on": null,
   "report_hide": 0,
   "reqd": 0,
   "search_index": 0,
   "translatable": 1,
   "unique": 0,
   "width": null
  },
  {
   "_assign": null,
   "_comments": null,
   "_liked_by": null,
   "_user_tags": null,
   "allow_in_quick_entry": 0,
   "allow_on_submit": 0,
   "bold": 0,
   "collapsible": 0,
   "collapsible_depends_on": null,
   "columns": 0,
   "creation": "2022-05-29 15:33:37.478771",
   "default": null,
   "depends_on": null,
   "description": null,
   "docstatus": 0,
   "dt": "Sales Invoice",
   "fetch_from": null,
   "fetch_if_empty": 0,
   "fieldname": "related_party_dimension",
   "fieldtype": "Link",
   "hidden": 0,
   "hide_border": 0,
   "hide_days": 0,
   "hide_seconds": 0,
   "idx": 34,
   "ignore_user_permissions": 0,
   "ignore_xss_filter": 0,
   "in_global_search": 0,
   "in_list_view": 0,
   "in_preview": 0,
   "in_standard_filter": 0,
   "insert_after": "staff_balances_dimension",
   "label": "Related Party Dimension",
   "length": 0,
   "mandatory_depends_on": null,
   "modified": "2022-05-29 15:33:37.478771",
   "modified_by": "Administrator",
   "name": "Sales Invoice-related_party_dimension",
   "no_copy": 0,
   "non_negative": 0,
   "options": "Related Party Dimension",
   "owner": "Administrator",
   "parent": null,
   "parentfield": null,
   "parenttype": null,
   "permlevel": 0,
   "precision": "",
   "print_hide": 0,
   "print_hide_if_no_value": 0,
   "print_width": null,
   "read_only": 0,
   "read_only_depends_on": null,
   "report_hide": 0,
   "reqd": 0,
   "search_index": 0,
   "translatable": 1,
   "unique": 0,
   "width": null
  },
  {
   "_assign": null,
   "_comments": null,
   "_liked_by": null,
   "_user_tags": null,
   "allow_in_quick_entry": 0,
   "allow_on_submit": 0,
   "bold": 0,
   "collapsible": 0,
   "collapsible_depends_on": null,
   "columns": 0,
   "creation": "2022-05-29 15:34:31.372887",
   "default": null,
   "depends_on": null,
   "description": null,
   "docstatus": 0,
   "dt": "Sales Invoice",
   "fetch_from": null,
   "fetch_if_empty": 0,
   "fieldname": "other_assets_dimension",
   "fieldtype": "Link",
   "hidden": 0,
   "hide_border": 0,
   "hide_days": 0,
   "hide_seconds": 0,
   "idx": 26,
   "ignore_user_permissions": 0,
   "ignore_xss_filter": 0,
   "in_global_search": 0,
   "in_list_view": 0,
   "in_preview": 0,
   "in_standard_filter": 0,
   "insert_after": "vehicle_loan_dimension",
   "label": "Other Assets Dimension",
   "length": 0,
   "mandatory_depends_on": null,
   "modified": "2022-05-29 15:34:31.372887",
   "modified_by": "Administrator",
   "name": "Sales Invoice-other_assets_dimension",
   "no_copy": 0,
   "non_negative": 0,
   "options": "Other Assets Dimension",
   "owner": "Administrator",
   "parent": null,
   "parentfield": null,
   "parenttype": null,
   "permlevel": 0,
   "precision": "",
   "print_hide": 0,
   "print_hide_if_no_value": 0,
   "print_width": null,
   "read_only": 0,
   "read_only_depends_on": null,
   "report_hide": 0,
   "reqd": 0,
   "search_index": 0,
   "translatable": 1,
   "unique": 0,
   "width": null
  },
  {
   "_assign": null,
   "_comments": null,
   "_liked_by": null,
   "_user_tags": null,
   "allow_in_quick_entry": 0,
   "allow_on_submit": 0,
   "bold": 0,
   "collapsible": 0,
   "collapsible_depends_on": null,
   "columns": 0,
   "creation": "2022-05-29 15:35:26.907040",
   "default": null,
   "depends_on": null,
   "description": null,
   "docstatus": 0,
   "dt": "Sales Invoice",
   "fetch_from": null,
   "fetch_if_empty": 0,
   "fieldname": "staff_balances_dimension",
   "fieldtype": "Link",
   "hidden": 0,
   "hide_border": 0,
   "hide_days": 0,
   "hide_seconds": 0,
   "idx": 33,
   "ignore_user_permissions": 0,
   "ignore_xss_filter": 0,
   "in_global_search": 0,
   "in_list_view": 0,
   "in_preview": 0,
   "in_standard_filter": 0,
   "insert_after": "dimension_col_break",
   "label": "Staff Balances Dimension",
   "length": 0,
   "mandatory_depends_on": null,
   "modified": "2022-05-29 15:35:26.907040",
   "modified_by": "Administrator",
   "name": "Sales Invoice-staff_balances_dimension",
   "no_copy": 0,
   "non_negative": 0,
   "options": "Staff Balances Dimension",
   "owner": "Administrator",
   "parent": null,
   "parentfield": null,
   "parenttype": null,
   "permlevel": 0,
   "precision": "",
   "print_hide": 0,
   "print_hide_if_no_value": 0,
   "print_width": null,
   "read_only": 0,
   "read_only_depends_on": null,
   "report_hide": 0,
   "reqd": 0,
   "search_index": 0,
   "translatable": 1,
   "unique": 0,
   "width": null
  },
  {
   "_assign": null,
   "_comments": null,
   "_liked_by": null,
   "_user_tags": null,
   "allow_in_quick_entry": 0,
   "allow_on_submit": 0,
   "bold": 0,
   "collapsible": 0,
   "collapsible_depends_on": null,
   "columns": 0,
   "creation": "2022-05-29 15:36:20.199522",
   "default": null,
   "depends_on": null,
   "description": null,
   "docstatus": 0,
   "dt": "Sales Invoice",
   "fetch_from": null,
   "fetch_if_empty": 0,
   "fieldname": "imprest_account_dimension",
   "fieldtype": "Link",
   "hidden": 0,
   "hide_border": 0,
   "hide_days": 0,
   "hide_seconds": 0,
   "idx": 28,
   "ignore_user_permissions": 0,
   "ignore_xss_filter": 0,
   "in_global_search": 0,
   "in_list_view": 0,
   "in_preview": 0,
   "in_standard_filter": 0,
   "insert_after": "motor_vehicle_expenses_dimension",
   "label": "Imprest Account Dimension",
   "length": 0,
   "mandatory_depends_on": null,
   "modified": "2022-05-29 15:36:20.199522",
   "modified_by": "Administrator",
   "name": "Sales Invoice-imprest_account_dimension",
   "no_copy": 0,
   "non_negative": 0,
   "options": "Imprest Account Dimension",
   "owner": "Administrator",
   "parent": null,
   "parentfield": null,
   "parenttype": null,
   "permlevel": 0,
   "precision": "",
   "print_hide": 0,
   "print_hide_if_no_value": 0,
   "print_width": null,
   "read_only": 0,
   "read_only_depends_on": null,
   "report_hide": 0,
   "reqd": 0,
   "search_index": 0,
   "translatable": 1,
   "unique": 0,
   "width": null
  },
  {
   "_assign": null,
   "_comments": null,
   "_liked_by": null,
   "_user_tags": null,
   "allow_in_quick_entry": 0,
   "allow_on_submit": 0,
   "bold": 0,
   "collapsible": 0,
   "collapsible_depends_on": null,
   "columns": 0,
   "creation": "2022-05-29 15:37:14.420743",
   "default": null,
   "depends_on": null,
   "description": null,
   "docstatus": 0,
   "dt": "Sales Invoice",
   "fetch_from": null,
   "fetch_if_empty": 0,
   "fieldname": "deposit_assets_dimension",
   "fieldtype": "Link",
   "hidden": 0,
   "hide_border": 0,
   "hide_days": 0,
   "hide_seconds": 0,
   "idx": 38,
   "ignore_user_permissions": 0,
   "ignore_xss_filter": 0,
   "in_global_search": 0,
   "in_list_view": 0,
   "in_preview": 0,
   "in_standard_filter": 0,
   "insert_after": "direct_expenses_dimension",
   "label": "Deposit Assets Dimension",
   "length": 0,
   "mandatory_depends_on": null,
   "modified": "2022-05-29 15:37:14.420743",
   "modified_by": "Administrator",
   "name": "Sales Invoice-deposit_assets_dimension",
   "no_copy": 0,
   "non_negative": 0,
   "options": "Deposit Assets Dimension",
   "owner": "Administrator",
   "parent": null,
   "parentfield": null,
   "parenttype": null,
   "permlevel": 0,
   "precision": "",
   "print_hide": 0,
   "print_hide_if_no_value": 0,
   "print_width": null,
   "read_only": 0,
   "read_only_depends_on": null,
   "report_hide": 0,
   "reqd": 0,
   "search_index": 0,
   "translatable": 1,
   "unique": 0,
   "width": null
  },
  {
   "_assign": null,
   "_comments": null,
   "_liked_by": null,
   "_user_tags": null,
   "allow_in_quick_entry": 0,
   "allow_on_submit": 0,
   "bold": 0,
   "collapsible": 0,
   "collapsible_depends_on": null,
   "columns": 0,
   "creation": "2022-05-29 15:38:27.931571",
   "default": null,
   "depends_on": null,
   "description": null,
   "docstatus": 0,
   "dt": "Sales Invoice",
   "fetch_from": null,
   "fetch_if_empty": 0,
   "fieldname": "cash_dimension",
   "fieldtype": "Link",
   "hidden": 0,
   "hide_border": 0,
   "hide_days": 0,
   "hide_seconds": 0,
   "idx": 29,
   "ignore_user_permissions": 0,
   "ignore_xss_filter": 0,
   "in_global_search": 0,
   "in_list_view": 0,
   "in_preview": 0,
   "in_standard_filter": 0,
   "insert_after": "imprest_account_dimension",
   "label": "Cash Dimension",
   "length": 0,
   "mandatory_depends_on": null,
   "modified": "2022-05-29 15:38:27.931571",
   "modified_by": "Administrator",
   "name": "Sales Invoice-cash_dimension",
   "no_copy": 0,
   "non_negative": 0,
   "options": "Cash Dimension",
   "owner": "Administrator",
   "parent": null,
   "parentfield": null,
   "parenttype": null,
   "permlevel": 0,
   "precision": "",
   "print_hide": 0,
   "print_hide_if_no_value": 0,
   "print_width": null,
   "read_only": 0,
   "read_only_depends_on": null,
   "report_hide": 0,
   "reqd": 0,
   "search_index": 0,
   "translatable": 1,
   "unique": 0,
   "width": null
  },
  {
   "_assign": null,
   "_comments": null,
   "_liked_by": null,
   "_user_tags": null,
   "allow_in_quick_entry": 0,
   "allow_on_submit": 0,
   "bold": 0,
   "collapsible": 1,
   "collapsible_depends_on": null,
   "columns": 0,
   "creation": "2022-06-06 13:44:39.296227",
   "default": null,
   "depends_on": null,
   "description": null,
   "docstatus": 0,
   "dt": "Sales Invoice",
   "fetch_from": null,
   "fetch_if_empty": 0,
   "fieldname": "tally_details",
   "fieldtype": "Section Break",
   "hidden": 0,
   "hide_border": 0,
   "hide_days": 0,
   "hide_seconds": 0,
   "idx": 212,
   "ignore_user_permissions": 0,
   "ignore_xss_filter": 0,
   "in_global_search": 0,
   "in_list_view": 0,
   "in_preview": 0,
   "in_standard_filter": 0,
   "insert_after": "tourist_tax_return",
   "label": "Tally Details",
   "length": 0,
   "mandatory_depends_on": null,
   "modified": "2022-06-06 13:44:39.296227",
   "modified_by": "Administrator",
   "name": "Sales Invoice-tally_details",
   "no_copy": 0,
   "non_negative": 0,
   "options": null,
   "owner": "Administrator",
   "parent": null,
   "parentfield": null,
   "parenttype": null,
   "permlevel": 0,
   "precision": "",
   "print_hide": 0,
   "print_hide_if_no_value": 0,
   "print_width": null,
   "read_only": 0,
   "read_only_depends_on": null,
   "report_hide": 0,
   "reqd": 0,
   "search_index": 0,
   "translatable": 0,
   "unique": 0,
   "width": null
  },
  {
   "_assign": null,
   "_comments": null,
   "_liked_by": null,
   "_user_tags": null,
   "allow_in_quick_entry": 0,
   "allow_on_submit": 0,
   "bold": 0,
   "collapsible": 0,
   "collapsible_depends_on": null,
   "columns": 0,
   "creation": "2022-06-06 13:44:39.864774",
   "default": null,
   "depends_on": null,
   "description": null,
   "docstatus": 0,
   "dt": "Sales Invoice",
   "fetch_from": null,
   "fetch_if_empty": 0,
   "fieldname": "tally_pk",
   "fieldtype": "Data",
   "hidden": 0,
   "hide_border": 0,
   "hide_days": 0,
   "hide_seconds": 0,
   "idx": 213,
   "ignore_user_permissions": 0,
   "ignore_xss_filter": 0,
   "in_global_search": 0,
   "in_list_view": 0,
   "in_preview": 0,
   "in_standard_filter": 0,
   "insert_after": "tally_details",
   "label": "Tally PK",
   "length": 0,
   "mandatory_depends_on": null,
   "modified": "2022-06-06 13:44:39.864774",
   "modified_by": "Administrator",
   "name": "Sales Invoice-tally_pk",
   "no_copy": 0,
   "non_negative": 0,
   "options": null,
   "owner": "Administrator",
   "parent": null,
   "parentfield": null,
   "parenttype": null,
   "permlevel": 0,
   "precision": "",
   "print_hide": 0,
   "print_hide_if_no_value": 0,
   "print_width": null,
   "read_only": 0,
   "read_only_depends_on": null,
   "report_hide": 0,
   "reqd": 0,
   "search_index": 0,
   "translatable": 1,
   "unique": 0,
   "width": null
  },
  {
   "_assign": null,
   "_comments": null,
   "_liked_by": null,
   "_user_tags": null,
   "allow_in_quick_entry": 0,
   "allow_on_submit": 0,
   "bold": 0,
   "collapsible": 0,
   "collapsible_depends_on": null,
   "columns": 0,
   "creation": "2022-06-06 13:44:40.328236",
   "default": null,
   "depends_on": null,
   "description": null,
   "docstatus": 0,
   "dt": "Sales Invoice",
   "fetch_from": null,
   "fetch_if_empty": 0,
   "fieldname": "tally_vat",
   "fieldtype": "Currency",
   "hidden": 0,
   "hide_border": 0,
   "hide_days": 0,
   "hide_seconds": 0,
   "idx": 214,
   "ignore_user_permissions": 0,
   "ignore_xss_filter": 0,
   "in_global_search": 0,
   "in_list_view": 0,
   "in_preview": 0,
   "in_standard_filter": 0,
   "insert_after": "tally_pk",
   "label": "Tally VAT",
   "length": 0,
   "mandatory_depends_on": null,
   "modified": "2022-06-06 13:44:40.328236",
   "modified_by": "Administrator",
   "name": "Sales Invoice-tally_vat",
   "no_copy": 0,
   "non_negative": 0,
   "options": null,
   "owner": "Administrator",
   "parent": null,
   "parentfield": null,
   "parenttype": null,
   "permlevel": 0,
   "precision": "",
   "print_hide": 0,
   "print_hide_if_no_value": 0,
   "print_width": null,
   "read_only": 0,
   "read_only_depends_on": null,
   "report_hide": 0,
   "reqd": 0,
   "search_index": 0,
   "translatable": 0,
   "unique": 0,
   "width": null
  },
  {
   "_assign": null,
   "_comments": null,
   "_liked_by": null,
   "_user_tags": null,
   "allow_in_quick_entry": 0,
   "allow_on_submit": 0,
   "bold": 0,
   "collapsible": 0,
   "collapsible_depends_on": null,
   "columns": 0,
   "creation": "2022-06-06 13:44:40.770477",
   "default": null,
   "depends_on": null,
   "description": null,
   "docstatus": 0,
   "dt": "Sales Invoice",
   "fetch_from": null,
   "fetch_if_empty": 0,
   "fieldname": "tally_currency",
   "fieldtype": "Link",
   "hidden": 0,
   "hide_border": 0,
   "hide_days": 0,
   "hide_seconds": 0,
   "idx": 215,
   "ignore_user_permissions": 0,
   "ignore_xss_filter": 0,
   "in_global_search": 0,
   "in_list_view": 0,
   "in_preview": 0,
   "in_standard_filter": 0,
   "insert_after": "tally_vat",
   "label": "Tally Currency",
   "length": 0,
   "mandatory_depends_on": null,
   "modified": "2022-06-06 13:44:40.770477",
   "modified_by": "Administrator",
   "name": "Sales Invoice-tally_currency",
   "no_copy": 0,
   "non_negative": 0,
   "options": "Currency",
   "owner": "Administrator",
   "parent": null,
   "parentfield": null,
   "parenttype": null,
   "permlevel": 0,
   "precision": "",
   "print_hide": 0,
   "print_hide_if_no_value": 0,
   "print_width": null,
   "read_only": 0,
   "read_only_depends_on": null,
   "report_hide": 0,
   "reqd": 0,
   "search_index": 0,
   "translatable": 0,
   "unique": 0,
   "width": null
  },
  {
   "_assign": null,
   "_comments": null,
   "_liked_by": null,
   "_user_tags": null,
   "allow_in_quick_entry": 0,
   "allow_on_submit": 0,
   "bold": 0,
   "collapsible": 0,
   "collapsible_depends_on": null,
   "columns": 0,
   "creation": "2022-06-06 13:44:41.204259",
   "default": null,
   "depends_on": null,
   "description": null,
   "docstatus": 0,
   "dt": "Sales Invoice",
   "fetch_from": null,
   "fetch_if_empty": 0,
   "fieldname": "column_break_212",
   "fieldtype": "Column Break",
   "hidden": 0,
   "hide_border": 0,
   "hide_days": 0,
   "hide_seconds": 0,
   "idx": 216,
   "ignore_user_permissions": 0,
   "ignore_xss_filter": 0,
   "in_global_search": 0,
   "in_list_view": 0,
   "in_preview": 0,
   "in_standard_filter": 0,
   "insert_after": "tally_currency",
   "label": null,
   "length": 0,
   "mandatory_depends_on": null,
   "modified": "2022-06-06 13:44:41.204259",
   "modified_by": "Administrator",
   "name": "Sales Invoice-column_break_212",
   "no_copy": 0,
   "non_negative": 0,
   "options": null,
   "owner": "Administrator",
   "parent": null,
   "parentfield": null,
   "parenttype": null,
   "permlevel": 0,
   "precision": "",
   "print_hide": 0,
   "print_hide_if_no_value": 0,
   "print_width": null,
   "read_only": 0,
   "read_only_depends_on": null,
   "report_hide": 0,
   "reqd": 0,
   "search_index": 0,
   "translatable": 0,
   "unique": 0,
   "width": null
  },
  {
   "_assign": null,
   "_comments": null,
   "_liked_by": null,
   "_user_tags": null,
   "allow_in_quick_entry": 0,
   "allow_on_submit": 0,
   "bold": 0,
   "collapsible": 0,
   "collapsible_depends_on": null,
   "columns": 0,
   "creation": "2022-06-06 13:44:41.636965",
   "default": null,
   "depends_on": null,
   "description": null,
   "docstatus": 0,
   "dt": "Sales Invoice",
   "fetch_from": null,
   "fetch_if_empty": 0,
   "fieldname": "tally_rate",
   "fieldtype": "Currency",
   "hidden": 0,
   "hide_border": 0,
   "hide_days": 0,
   "hide_seconds": 0,
   "idx": 217,
   "ignore_user_permissions": 0,
   "ignore_xss_filter": 0,
   "in_global_search": 0,
   "in_list_view": 0,
   "in_preview": 0,
   "in_standard_filter": 0,
   "insert_after": "column_break_212",
   "label": "Tally Rate",
   "length": 0,
   "mandatory_depends_on": null,
   "modified": "2022-06-06 13:44:41.636965",
   "modified_by": "Administrator",
   "name": "Sales Invoice-tally_rate",
   "no_copy": 0,
   "non_negative": 0,
   "options": null,
   "owner": "Administrator",
   "parent": null,
   "parentfield": null,
   "parenttype": null,
   "permlevel": 0,
   "precision": "",
   "print_hide": 0,
   "print_hide_if_no_value": 0,
   "print_width": null,
   "read_only": 0,
   "read_only_depends_on": null,
   "report_hide": 0,
   "reqd": 0,
   "search_index": 0,
   "translatable": 0,
   "unique": 0,
   "width": null
  },
  {
   "_assign": null,
   "_comments": null,
   "_liked_by": null,
   "_user_tags": null,
   "allow_in_quick_entry": 0,
   "allow_on_submit": 0,
   "bold": 0,
   "collapsible": 0,
   "collapsible_depends_on": null,
   "columns": 0,
   "creation": "2022-06-06 13:44:42.140746",
   "default": null,
   "depends_on": null,
   "description": null,
   "docstatus": 0,
   "dt": "Sales Invoice",
   "fetch_from": null,
   "fetch_if_empty": 0,
   "fieldname": "tally_order_total",
   "fieldtype": "Currency",
   "hidden": 0,
   "hide_border": 0,
   "hide_days": 0,
   "hide_seconds": 0,
   "idx": 218,
   "ignore_user_permissions": 0,
   "ignore_xss_filter": 0,
   "in_global_search": 0,
   "in_list_view": 0,
   "in_preview": 0,
   "in_standard_filter": 0,
   "insert_after": "tally_rate",
   "label": "Tally Order Total",
   "length": 0,
   "mandatory_depends_on": null,
   "modified": "2022-06-06 13:44:42.140746",
   "modified_by": "Administrator",
   "name": "Sales Invoice-tally_order_total",
   "no_copy": 0,
   "non_negative": 0,
   "options": null,
   "owner": "Administrator",
   "parent": null,
   "parentfield": null,
   "parenttype": null,
   "permlevel": 0,
   "precision": "",
   "print_hide": 0,
   "print_hide_if_no_value": 0,
   "print_width": null,
   "read_only": 0,
   "read_only_depends_on": null,
   "report_hide": 0,
   "reqd": 0,
   "search_index": 0,
   "translatable": 0,
   "unique": 0,
   "width": null
  },
  {
   "_assign": null,
   "_comments": null,
   "_liked_by": null,
   "_user_tags": null,
   "allow_in_quick_entry": 0,
   "allow_on_submit": 0,
   "bold": 0,
   "collapsible": 0,
   "collapsible_depends_on": null,
   "columns": 0,
   "creation": "2022-06-06 13:44:42.679357",
   "default": null,
   "depends_on": null,
   "description": null,
   "docstatus": 0,
   "dt": "Sales Invoice",
   "fetch_from": null,
   "fetch_if_empty": 0,
   "fieldname": "tally_discount_total",
   "fieldtype": "Currency",
   "hidden": 0,
   "hide_border": 0,
   "hide_days": 0,
   "hide_seconds": 0,
   "idx": 220,
   "ignore_user_permissions": 0,
   "ignore_xss_filter": 0,
   "in_global_search": 0,
   "in_list_view": 0,
   "in_preview": 0,
   "in_standard_filter": 0,
   "insert_after": "tally_discount",
   "label": "Tally Discount Total",
   "length": 0,
   "mandatory_depends_on": null,
   "modified": "2022-06-06 13:44:42.679357",
   "modified_by": "Administrator",
   "name": "Sales Invoice-tally_discount_total",
   "no_copy": 0,
   "non_negative": 0,
   "options": null,
   "owner": "Administrator",
   "parent": null,
   "parentfield": null,
   "parenttype": null,
   "permlevel": 0,
   "precision": "",
   "print_hide": 0,
   "print_hide_if_no_value": 0,
   "print_width": null,
   "read_only": 0,
   "read_only_depends_on": null,
   "report_hide": 0,
   "reqd": 0,
   "search_index": 0,
   "translatable": 0,
   "unique": 0,
   "width": null
  },
  {
   "_assign": null,
   "_comments": null,
   "_liked_by": null,
   "_user_tags": null,
   "allow_in_quick_entry": 0,
   "allow_on_submit": 0,
   "bold": 0,
   "collapsible": 0,
   "collapsible_depends_on": null,
   "columns": 0,
   "creation": "2022-06-06 14:06:09.652514",
   "default": null,
   "depends_on": null,
   "description": null,
   "docstatus": 0,
   "dt": "Sales Invoice",
   "fetch_from": null,
   "fetch_if_empty": 0,
   "fieldname": "tally_discount",
   "fieldtype": "Currency",
   "hidden": 0,
   "hide_border": 0,
   "hide_days": 0,
   "hide_seconds": 0,
   "idx": 219,
   "ignore_user_permissions": 0,
   "ignore_xss_filter": 0,
   "in_global_search": 0,
   "in_list_view": 0,
   "in_preview": 0,
   "in_standard_filter": 0,
   "insert_after": "tally_order_total",
   "label": "Tally Discount",
   "length": 0,
   "mandatory_depends_on": null,
   "modified": "2022-06-06 14:06:09.652514",
   "modified_by": "Administrator",
   "name": "Sales Invoice-tally_discount",
   "no_copy": 0,
   "non_negative": 0,
   "options": null,
   "owner": "Administrator",
   "parent": null,
   "parentfield": null,
   "parenttype": null,
   "permlevel": 0,
   "precision": "",
   "print_hide": 0,
   "print_hide_if_no_value": 0,
   "print_width": null,
   "read_only": 0,
   "read_only_depends_on": null,
   "report_hide": 0,
   "reqd": 0,
   "search_index": 0,
   "translatable": 0,
   "unique": 0,
   "width": null
  },
  {
   "_assign": null,
   "_comments": null,
   "_liked_by": null,
   "_user_tags": null,
   "allow_in_quick_entry": 0,
   "allow_on_submit": 0,
   "bold": 0,
   "collapsible": 0,
   "collapsible_depends_on": null,
   "columns": 0,
   "creation": "2022-10-16 09:18:19.687418",
   "default": null,
   "depends_on": null,
   "description": null,
   "docstatus": 0,
   "dt": "Sales Invoice",
   "fetch_from": null,
   "fetch_if_empty": 0,
   "fieldname": "print_without_amount",
   "fieldtype": "Check",
   "hidden": 0,
   "hide_border": 0,
   "hide_days": 0,
   "hide_seconds": 0,
   "idx": 168,
   "ignore_user_permissions": 0,
   "ignore_xss_filter": 0,
   "in_global_search": 0,
   "in_list_view": 0,
   "in_preview": 0,
   "in_standard_filter": 0,
   "insert_after": "group_same_items",
   "label": "Print Without Amount",
   "length": 0,
   "mandatory_depends_on": null,
   "modified": "2022-10-16 09:18:19.687418",
   "modified_by": "Administrator",
   "name": "Sales Invoice-print_without_amount",
   "no_copy": 0,
   "non_negative": 0,
   "options": null,
   "owner": "Administrator",
   "parent": null,
   "parentfield": null,
   "parenttype": null,
   "permlevel": 0,
   "precision": "",
   "print_hide": 0,
   "print_hide_if_no_value": 0,
   "print_width": null,
   "read_only": 0,
   "read_only_depends_on": null,
   "report_hide": 0,
   "reqd": 0,
   "search_index": 0,
   "translatable": 0,
   "unique": 0,
   "width": null
  },
  {
   "_assign": null,
   "_comments": null,
   "_liked_by": null,
   "_user_tags": null,
   "allow_in_quick_entry": 0,
   "allow_on_submit": 1,
   "bold": 0,
   "collapsible": 0,
   "collapsible_depends_on": null,
   "columns": 0,
   "creation": "2022-10-16 10:24:11.642801",
   "default": null,
   "depends_on": null,
   "description": null,
   "docstatus": 0,
   "dt": "Sales Invoice",
   "fetch_from": null,
   "fetch_if_empty": 0,
   "fieldname": "approved_by",
   "fieldtype": "Link",
   "hidden": 0,
   "hide_border": 0,
   "hide_days": 0,
   "hide_seconds": 0,
   "idx": 181,
   "ignore_user_permissions": 0,
   "ignore_xss_filter": 0,
   "in_global_search": 0,
   "in_list_view": 0,
   "in_preview": 0,
   "in_standard_filter": 0,
   "insert_after": "campaign",
   "label": "Approved By",
   "length": 0,
   "mandatory_depends_on": null,
   "modified": "2022-10-16 10:24:11.642801",
   "modified_by": "Administrator",
   "name": "Sales Invoice-approved_by",
   "no_copy": 0,
   "non_negative": 0,
   "options": "User",
   "owner": "Administrator",
   "parent": null,
   "parentfield": null,
   "parenttype": null,
   "permlevel": 0,
   "precision": "",
   "print_hide": 0,
   "print_hide_if_no_value": 0,
   "print_width": null,
   "read_only": 0,
   "read_only_depends_on": null,
   "report_hide": 0,
   "reqd": 0,
   "search_index": 0,
   "translatable": 0,
   "unique": 0,
   "width": null
  },
  {
   "_assign": null,
   "_comments": null,
   "_liked_by": null,
   "_user_tags": null,
   "allow_in_quick_entry": 0,
   "allow_on_submit": 1,
   "bold": 0,
   "collapsible": 0,
   "collapsible_depends_on": null,
   "columns": 0,
   "creation": "2022-10-16 10:24:12.783611",
   "default": null,
   "depends_on": null,
   "description": null,
   "docstatus": 0,
   "dt": "Sales Invoice",
   "fetch_from": null,
   "fetch_if_empty": 0,
   "fieldname": "received_by",
   "fieldtype": "Link",
   "hidden": 0,
   "hide_border": 0,
   "hide_days": 0,
   "hide_seconds": 0,
   "idx": 182,
   "ignore_user_permissions": 0,
   "ignore_xss_filter": 0,
   "in_global_search": 0,
   "in_list_view": 0,
   "in_preview": 0,
   "in_standard_filter": 0,
   "insert_after": "approved_by",
   "label": "Received By",
   "length": 0,
   "mandatory_depends_on": null,
   "modified": "2022-10-16 10:24:12.783611",
   "modified_by": "Administrator",
   "name": "Sales Invoice-received_by",
   "no_copy": 0,
   "non_negative": 0,
   "options": "User",
   "owner": "Administrator",
   "parent": null,
   "parentfield": null,
   "parenttype": null,
   "permlevel": 0,
   "precision": "",
   "print_hide": 0,
   "print_hide_if_no_value": 0,
   "print_width": null,
   "read_only": 0,
   "read_only_depends_on": null,
   "report_hide": 0,
   "reqd": 0,
   "search_index": 0,
   "translatable": 0,
   "unique": 0,
   "width": null
  }
 ],
 "custom_perms": [
  {
   "_assign": null,
   "_comments": null,
   "_liked_by": null,
   "_user_tags": null,
   "amend": 0,
   "cancel": 0,
   "create": 0,
   "creation": "2022-01-25 10:29:57.771398",
   "delete": 0,
   "docstatus": 0,
   "email": 0,
   "export": 0,
   "idx": 3,
   "if_owner": 0,
   "import": 0,
   "modified": "2022-05-25 17:32:01.220061",
   "modified_by": "Administrator",
   "name": "445f4340e0",
   "owner": "Administrator",
   "parent": "Sales Invoice",
   "parentfield": "permissions",
   "parenttype": "DocType",
   "permlevel": 1,
   "print": 0,
   "read": 1,
   "report": 0,
   "role": "Accounts Manager",
   "select": 0,
   "set_user_permissions": 0,
   "share": 0,
   "submit": 0,
   "write": 1
  },
  {
   "_assign": null,
   "_comments": null,
   "_liked_by": null,
   "_user_tags": null,
   "amend": 0,
   "cancel": 0,
   "create": 0,
   "creation": "2022-01-25 10:29:57.771398",
   "delete": 0,
   "docstatus": 0,
   "email": 0,
   "export": 0,
   "idx": 4,
   "if_owner": 0,
   "import": 0,
   "modified": "2022-05-25 17:32:01.238983",
   "modified_by": "Administrator",
   "name": "ce4f800c9f",
   "owner": "Administrator",
   "parent": "Sales Invoice",
   "parentfield": "permissions",
   "parenttype": "DocType",
   "permlevel": 1,
   "print": 0,
   "read": 1,
   "report": 0,
   "role": "All",
   "select": 0,
   "set_user_permissions": 0,
   "share": 0,
   "submit": 0,
   "write": 0
  },
  {
   "_assign": null,
   "_comments": null,
   "_liked_by": null,
   "_user_tags": null,
   "amend": 1,
   "cancel": 0,
   "create": 1,
   "creation": "2022-01-25 10:29:57.771398",
   "delete": 0,
   "docstatus": 0,
   "email": 1,
   "export": 0,
   "idx": 2,
   "if_owner": 0,
   "import": 0,
   "modified": "2022-05-25 17:32:01.255214",
   "modified_by": "Administrator",
   "name": "2c5ed4cf67",
   "owner": "Administrator",
   "parent": "Sales Invoice",
   "parentfield": "permissions",
   "parenttype": "DocType",
   "permlevel": 0,
   "print": 1,
   "read": 1,
   "report": 1,
   "role": "Accounts User",
   "select": 0,
   "set_user_permissions": 0,
   "share": 1,
   "submit": 1,
   "write": 1
  },
  {
   "_assign": null,
   "_comments": null,
   "_liked_by": null,
   "_user_tags": null,
   "amend": 1,
   "cancel": 1,
   "create": 1,
   "creation": "2022-01-25 10:29:57.771398",
   "delete": 1,
   "docstatus": 0,
   "email": 1,
   "export": 0,
   "idx": 1,
   "if_owner": 0,
   "import": 0,
   "modified": "2022-05-25 17:32:01.271721",
   "modified_by": "Administrator",
   "name": "4330c00047",
   "owner": "Administrator",
   "parent": "Sales Invoice",
   "parentfield": "permissions",
   "parenttype": "DocType",
   "permlevel": 0,
   "print": 1,
   "read": 1,
   "report": 1,
   "role": "Accounts Manager",
   "select": 0,
   "set_user_permissions": 0,
   "share": 1,
   "submit": 1,
   "write": 1
  },
  {
   "_assign": null,
   "_comments": null,
   "_liked_by": null,
   "_user_tags": null,
   "amend": 0,
   "cancel": 0,
   "create": 0,
   "creation": "2022-05-25 17:32:01.292568",
   "delete": 0,
   "docstatus": 0,
   "email": 0,
   "export": 1,
   "idx": 0,
   "if_owner": 0,
   "import": 0,
   "modified": "2022-05-25 17:32:01.385121",
   "modified_by": "Administrator",
   "name": "0c6a035d25",
   "owner": "Administrator",
   "parent": "Sales Invoice",
   "parentfield": "permissions",
   "parenttype": "DocType",
   "permlevel": 0,
   "print": 0,
   "read": 0,
   "report": 0,
   "role": "Employee Self Service",
   "select": 1,
   "set_user_permissions": 0,
   "share": 0,
   "submit": 0,
   "write": 0
  }
 ],
 "doctype": "Sales Invoice",
 "property_setters": [
  {
   "_assign": null,
   "_comments": null,
   "_liked_by": null,
   "_user_tags": null,
   "creation": "2022-09-22 12:39:21.724086",
   "default_value": null,
   "doc_type": "Sales Invoice",
   "docstatus": 0,
   "doctype_or_field": "DocField",
   "field_name": "in_words",
   "idx": 0,
   "modified": "2022-09-22 12:39:21.724086",
   "modified_by": "Administrator",
   "name": "Sales Invoice-in_words-print_hide",
   "owner": "Administrator",
   "parent": null,
   "parentfield": null,
   "parenttype": null,
   "property": "print_hide",
   "property_type": "Check",
   "row_name": null,
   "value": "0"
  },
  {
   "_assign": null,
   "_comments": null,
   "_liked_by": null,
   "_user_tags": null,
   "creation": "2022-09-22 12:39:21.611660",
   "default_value": null,
   "doc_type": "Sales Invoice",
   "docstatus": 0,
   "doctype_or_field": "DocField",
   "field_name": "in_words",
   "idx": 0,
   "modified": "2022-09-22 12:39:21.611660",
   "modified_by": "Administrator",
   "name": "Sales Invoice-in_words-hidden",
   "owner": "Administrator",
   "parent": null,
   "parentfield": null,
   "parenttype": null,
   "property": "hidden",
   "property_type": "Check",
   "row_name": null,
   "value": "0"
  },
  {
   "_assign": null,
   "_comments": null,
   "_liked_by": null,
   "_user_tags": null,
   "creation": "2022-09-22 12:39:20.634159",
   "default_value": null,
   "doc_type": "Sales Invoice",
   "docstatus": 0,
   "doctype_or_field": "DocField",
   "field_name": "disable_rounded_total",
   "idx": 0,
   "modified": "2022-09-22 12:39:20.634159",
   "modified_by": "Administrator",
   "name": "Sales Invoice-disable_rounded_total-default",
   "owner": "Administrator",
   "parent": null,
   "parentfield": null,
   "parenttype": null,
   "property": "default",
   "property_type": "Text",
   "row_name": null,
   "value": "1"
  },
  {
   "_assign": null,
   "_comments": null,
   "_liked_by": null,
   "_user_tags": null,
   "creation": "2022-09-22 12:39:20.597909",
   "default_value": null,
   "doc_type": "Sales Invoice",
   "docstatus": 0,
   "doctype_or_field": "DocField",
   "field_name": "rounded_total",
   "idx": 0,
   "modified": "2022-09-22 12:39:20.597909",
   "modified_by": "Administrator",
   "name": "Sales Invoice-rounded_total-print_hide",
   "owner": "Administrator",
   "parent": null,
   "parentfield": null,
   "parenttype": null,
   "property": "print_hide",
   "property_type": "Check",
   "row_name": null,
   "value": "1"
  },
  {
   "_assign": null,
   "_comments": null,
   "_liked_by": null,
   "_user_tags": null,
   "creation": "2022-09-22 12:39:20.543382",
   "default_value": null,
   "doc_type": "Sales Invoice",
   "docstatus": 0,
   "doctype_or_field": "DocField",
   "field_name": "rounded_total",
   "idx": 0,
   "modified": "2022-09-22 12:39:20.543382",
   "modified_by": "Administrator",
   "name": "Sales Invoice-rounded_total-hidden",
   "owner": "Administrator",
   "parent": null,
   "parentfield": null,
   "parenttype": null,
   "property": "hidden",
   "property_type": "Check",
   "row_name": null,
   "value": "1"
  },
  {
   "_assign": null,
   "_comments": null,
   "_liked_by": null,
   "_user_tags": null,
   "creation": "2022-09-22 12:39:20.503599",
   "default_value": null,
   "doc_type": "Sales Invoice",
   "docstatus": 0,
   "doctype_or_field": "DocField",
   "field_name": "base_rounded_total",
   "idx": 0,
   "modified": "2022-09-22 12:39:20.503599",
   "modified_by": "Administrator",
   "name": "Sales Invoice-base_rounded_total-print_hide",
   "owner": "Administrator",
   "parent": null,
   "parentfield": null,
   "parenttype": null,
   "property": "print_hide",
   "property_type": "Check",
   "row_name": null,
   "value": "1"
  },
  {
   "_assign": null,
   "_comments": null,
   "_liked_by": null,
   "_user_tags": null,
   "creation": "2022-09-22 12:39:20.465118",
   "default_value": null,
   "doc_type": "Sales Invoice",
   "docstatus": 0,
   "doctype_or_field": "DocField",
   "field_name": "base_rounded_total",
   "idx": 0,
   "modified": "2022-09-22 12:39:20.465118",
   "modified_by": "Administrator",
   "name": "Sales Invoice-base_rounded_total-hidden",
   "owner": "Administrator",
   "parent": null,
   "parentfield": null,
   "parenttype": null,
   "property": "hidden",
   "property_type": "Check",
   "row_name": null,
   "value": "1"
  },
  {
   "_assign": null,
   "_comments": null,
   "_liked_by": null,
   "_user_tags": null,
   "creation": "2022-07-21 08:30:45.999589",
   "default_value": null,
   "doc_type": "Sales Invoice",
   "docstatus": 0,
   "doctype_or_field": "DocField",
   "field_name": "tax_id",
   "idx": 0,
   "modified": "2022-07-21 08:30:45.999589",
   "modified_by": "Administrator",
   "name": "Sales Invoice-tax_id-print_hide",
   "owner": "Administrator",
   "parent": null,
   "parentfield": null,
   "parenttype": null,
   "property": "print_hide",
   "property_type": "Check",
   "row_name": null,
   "value": "0"
  },
  {
   "_assign": null,
   "_comments": null,
   "_liked_by": null,
   "_user_tags": null,
   "creation": "2022-07-21 08:30:45.970383",
   "default_value": null,
   "doc_type": "Sales Invoice",
   "docstatus": 0,
   "doctype_or_field": "DocField",
   "field_name": "tax_id",
   "idx": 0,
   "modified": "2022-07-21 08:30:45.970383",
   "modified_by": "Administrator",
   "name": "Sales Invoice-tax_id-hidden",
   "owner": "Administrator",
   "parent": null,
   "parentfield": null,
   "parenttype": null,
   "property": "hidden",
   "property_type": "Check",
   "row_name": null,
   "value": "0"
  },
  {
   "_assign": null,
   "_comments": null,
   "_liked_by": null,
   "_user_tags": null,
   "creation": "2022-06-11 19:58:37.310275",
   "default_value": null,
   "doc_type": "Sales Invoice",
   "docstatus": 0,
   "doctype_or_field": "DocField",
   "field_name": "additional_discount_account",
   "idx": 0,
   "modified": "2022-06-11 19:58:37.310275",
   "modified_by": "Administrator",
   "name": "Sales Invoice-additional_discount_account-mandatory_depends_on",
   "owner": "Administrator",
   "parent": null,
   "parentfield": null,
   "parenttype": null,
   "property": "mandatory_depends_on",
   "property_type": "Code",
   "row_name": null,
   "value": ""
  },
  {
   "_assign": null,
   "_comments": null,
   "_liked_by": null,
   "_user_tags": null,
   "creation": "2022-06-11 19:58:37.276364",
   "default_value": null,
   "doc_type": "Sales Invoice",
   "docstatus": 0,
   "doctype_or_field": "DocField",
   "field_name": "additional_discount_account",
   "idx": 0,
   "modified": "2022-06-11 19:58:37.276364",
   "modified_by": "Administrator",
   "name": "Sales Invoice-additional_discount_account-hidden",
   "owner": "Administrator",
   "parent": null,
   "parentfield": null,
   "parenttype": null,
   "property": "hidden",
   "property_type": "Check",
   "row_name": null,
   "value": "1"
  },
  {
   "_assign": null,
   "_comments": null,
   "_liked_by": null,
   "_user_tags": null,
   "creation": "2022-06-11 19:58:36.895190",
   "default_value": null,
   "doc_type": "Sales Invoice",
   "docstatus": 0,
   "doctype_or_field": "DocField",
   "field_name": "payment_schedule",
   "idx": 0,
   "modified": "2022-06-11 19:58:36.895190",
   "modified_by": "Administrator",
   "name": "Sales Invoice-payment_schedule-print_hide",
   "owner": "Administrator",
   "parent": null,
   "parentfield": null,
   "parenttype": null,
   "property": "print_hide",
   "property_type": "Check",
   "row_name": null,
   "value": "1"
  },
  {
   "_assign": null,
   "_comments": null,
   "_liked_by": null,
   "_user_tags": null,
   "creation": "2022-06-11 19:58:36.844067",
   "default_value": null,
   "doc_type": "Sales Invoice",
   "docstatus": 0,
   "doctype_or_field": "DocField",
   "field_name": "due_date",
   "idx": 0,
   "modified": "2022-06-11 19:58:36.844067",
   "modified_by": "Administrator",
   "name": "Sales Invoice-due_date-print_hide",
   "owner": "Administrator",
   "parent": null,
   "parentfield": null,
   "parenttype": null,
   "property": "print_hide",
   "property_type": "Check",
   "row_name": null,
   "value": "0"
  },
  {
   "_assign": null,
   "_comments": null,
   "_liked_by": null,
   "_user_tags": null,
   "creation": "2022-05-25 16:54:49.292715",
   "default_value": null,
   "doc_type": "Sales Invoice",
   "docstatus": 0,
   "doctype_or_field": "DocField",
   "field_name": "scan_barcode",
   "idx": 0,
   "modified": "2022-05-25 16:54:49.292715",
   "modified_by": "Administrator",
   "name": "Sales Invoice-scan_barcode-hidden",
   "owner": "Administrator",
   "parent": null,
   "parentfield": null,
   "parenttype": null,
   "property": "hidden",
   "property_type": "Check",
   "row_name": null,
   "value": "0"
  }
 ],
 "sync_on_migrate": 1
}